{
  "entityType" : "DEVICE",
  "entity" : {
    "additionalInfo" : null,
    "customerId" : {
      "entityType" : "CUSTOMER",
      "id" : "a16d7d60-9089-11ed-bd23-bb2e36863f7a"
    },
    "deviceData" : {
      "configuration" : {
        "type" : "DEFAULT"
      },
      "transportConfiguration" : {
        "type" : "DEFAULT"
      }
    },
    "deviceProfileId" : {
      "entityType" : "DEVICE_PROFILE",
      "id" : "a15c1840-9089-11ed-bd23-bb2e36863f7a"
    },
    "externalId" : {
      "entityType" : "DEVICE",
      "id" : "a1f264d0-9089-11ed-bd23-bb2e36863f7a"
    },
    "firmwareId" : null,
    "id" : {
      "entityType" : "DEVICE",
      "id" : "a1f264d0-9089-11ed-bd23-bb2e36863f7a"
    },
    "label" : "Back Door",
    "name" : "Door Sensor 4534",
    "ownerId" : {
      "entityType" : "CUSTOMER",
      "id" : "a16d7d60-9089-11ed-bd23-bb2e36863f7a"
    },
    "softwareId" : null,
    "type" : "Door Sensor"
  },
  "credentials" : {
    "credentialsId" : "kLiXM1j7fOTSWixT9YqK",
    "credentialsType" : "ACCESS_TOKEN",
    "credentialsValue" : null
  },
  "relations" : [ {
    "additionalInfo" : null,
    "from" : {
      "entityType" : "ASSET",
      "id" : "a182b310-9089-11ed-bd23-bb2e36863f7a"
    },
    "to" : {
      "entityType" : "DEVICE",
      "id" : "a1f264d0-9089-11ed-bd23-bb2e36863f7a"
    },
    "type" : "Contains",
    "typeGroup" : "COMMON"
  } ],
  "attributes" : {
    "SERVER_SCOPE" : [ {
      "booleanValue" : true,
      "doubleValue" : null,
      "jsonValue" : null,
      "key" : "active",
      "lastUpdateTs" : 1673315633112,
      "longValue" : null,
      "strValue" : null
    }, {
      "booleanValue" : null,
      "doubleValue" : null,
      "jsonValue" : null,
      "key" : "inactivityTimeout",
      "lastUpdateTs" : 1673315633095,
      "longValue" : 15768000000,
      "strValue" : null
    }, {
      "booleanValue" : null,
      "doubleValue" : null,
      "jsonValue" : null,
      "key" : "lastActivityTime",
      "lastUpdateTs" : 1673315633112,
      "longValue" : 1673315633102,
      "strValue" : null
    }, {
      "booleanValue" : null,
      "doubleValue" : null,
      "jsonValue" : null,
      "key" : "lowBatteryCriticalThreshold",
      "lastUpdateTs" : 1673315632038,
      "longValue" : 10,
      "strValue" : null
    }, {
      "booleanValue" : null,
      "doubleValue" : null,
      "jsonValue" : null,
      "key" : "lowBatteryMajorThreshold",
      "lastUpdateTs" : 1673315632038,
      "longValue" : 30,
      "strValue" : null
    }, {
      "booleanValue" : null,
      "doubleValue" : null,
      "jsonValue" : null,
      "key" : "maxDoorOpenDurationCriticalThreshold",
      "lastUpdateTs" : 1673315632038,
      "longValue" : 60,
      "strValue" : null
    }, {
      "booleanValue" : null,
      "doubleValue" : null,
      "jsonValue" : null,
      "key" : "maxDoorOpenDurationMajorThreshold",
      "lastUpdateTs" : 1673315632038,
      "longValue" : 30,
      "strValue" : null
    }, {
      "booleanValue" : null,
      "doubleValue" : null,
      "jsonValue" : null,
      "key" : "state",
      "lastUpdateTs" : 1673315634647,
      "longValue" : null,
      "strValue" : "critical"
    }, {
      "booleanValue" : null,
      "doubleValue" : 0.0867232290409743,
      "jsonValue" : null,
      "key" : "xPos",
      "lastUpdateTs" : 1673315632038,
      "longValue" : null,
      "strValue" : null
    }, {
      "booleanValue" : null,
      "doubleValue" : 0.0691862026256517,
      "jsonValue" : null,
      "key" : "yPos",
      "lastUpdateTs" : 1673315632038,
      "longValue" : null,
      "strValue" : null
    } ],
    "SHARED_SCOPE" : [ ]
  }
}